gfthings/.gfbin.py.swp
gfthings/Base.py
gfthings/Bin.py
gfthings/Edge.py
gfthings/GFProfile.py
gfthings/Pin.py
gfthings/__init__.py
gfthings/gfbase.py
gfthings/gfbin.py
gfthings/gfedge.py
gfthings/gfpin.py
gfthings/parameters.py
gfthings-0.8.0.dist-info/METADATA
gfthings-0.8.0.dist-info/WHEEL
gfthings-0.8.0.dist-info/entry_points.txt
gfthings-0.8.0.dist-info/RECORD
