Metadata-Version: 2.1
Name: gfthings
Version: 0.8.0
Summary: Paul's Gridfinity Things
License: CC BY-NC-SA 4.0
Author: Paul Bone
Author-email: paul@bone.id.au
Requires-Python: >=3.10,<3.14
Classifier: License :: Other/Proprietary License
Classifier: Operating System :: POSIX :: Linux
Classifier: Programming Language :: Python :: 3
Classifier: Programming Language :: Python :: 3.10
Classifier: Programming Language :: Python :: 3.11
Classifier: Programming Language :: Python :: 3.12
Classifier: Programming Language :: Python :: 3.13
Requires-Dist: build123d (>=0.9.1,<0.10.0)
